bloomy/__init__.py
bloomy/bloom.py
bloomy-0.0.2.dist-info/LICENSE
bloomy-0.0.2.dist-info/METADATA
bloomy-0.0.2.dist-info/WHEEL
bloomy-0.0.2.dist-info/top_level.txt
bloomy-0.0.2.dist-info/RECORD
