Metadata-Version: 2.1
Name: bloomy
Version: 0.0.2
Summary: An efficient and scalable bloom filter module built in pure python.
Home-page: https://github.com/shmam/bloomy
Author: Sam Crochet
Author-email: samuel.d.crochet@gmail.com
License: UNKNOWN
Platform: UNKNOWN
Classifier: Programming Language :: Python :: 3
Classifier: License :: OSI Approved :: MIT License
Classifier: Operating System :: OS Independent
